CHANGES.txt
CONTRIBUTORS.txt
LICENSE
MANIFEST.in
README.txt
setup.cfg
setup.py
pbp/__init__.py
pbp.recipe.noserunner.egg-info/PKG-INFO
pbp.recipe.noserunner.egg-info/SOURCES.txt
pbp.recipe.noserunner.egg-info/dependency_links.txt
pbp.recipe.noserunner.egg-info/entry_points.txt
pbp.recipe.noserunner.egg-info/namespace_packages.txt
pbp.recipe.noserunner.egg-info/not-zip-safe
pbp.recipe.noserunner.egg-info/requires.txt
pbp.recipe.noserunner.egg-info/top_level.txt
pbp/recipe/__init__.py
pbp/recipe/noserunner/README.txt
pbp/recipe/noserunner/__init__.py
pbp/recipe/noserunner/tests/__init__.py
pbp/recipe/noserunner/tests/test_docs.py