Metadata-Version: 1.0
Name: pbp.recipe.noserunner
Version: 0.2.4
Summary: Expert Python Programming - ZC Buildout runner for nose
Home-page: http://atomisator.ziade.org
Author: Tarek Ziade
Author-email: tarek@ziade.org
License: ZPL
Platform: UNKNOWN
Classifier: Framework :: Buildout
Classifier: Intended Audience :: Developers
Classifier: Topic :: Software Development :: Build Tools
Classifier: Topic :: Software Development :: Libraries :: Python Modules
Classifier: License :: OSI Approved :: Zope Public License
